{
    "title": "Vase of Flowers",
    "artist": "Jan Davidsz de Heem",
    "year": 1670,
    "description": "Vase of Flowers. Creator: Jan Davidsz de Heem. Date: 1670. Institution: Mauritshuis. Provider: Digitale Collectie. Providing Country: Netherlands. PD for Public Domain Mark",
    "image": "https://images.unsplash.com/photo-1579783900882-c0d3dad7b119?ixlib=rb-1.2.1&ixid=MnwxMjA3fDB8MHxwaG90by1wYWdlfHx8fGVufDB8fHx8&auto=format&fit=crop&w=816&q=80",
    "subject":{
        "subject_level0": "Inanimate Object",
        "subject_level1": ["Inanimate Object > Vase","Inanimate Object > Urn"],
        "subject_level2": "Inanimate Object > Vase > Floral Vase"
      },
    "color":["blue", "green"]

}